{
  "id": 424,
  "orgId": 1,
  "folderId": 668,
  "folderUid": "folder-PjWklf8Vz",
  "uid": "22IZBlrVk",
  "name": "TikTok Top Videos Title",
  "kind": 1,
  "type": "text",
  "description": "",
  "model": {
    "datasource": {
      "type": "grafana-bigquery-datasource",
      "uid": "qUaUqEk4k"
    },
    "description": "",
    "gridPos": {
      "h": 2,
      "w": 7,
      "x": 0,
      "y": 4
    },
    "id": 147,
    "libraryPanel": {
      "meta": {
        "connectedDashboards": 0,
        "created": "2023-07-07T09:44:53.966449489Z",
        "createdBy": {
          "avatarUrl": "/avatar/4ef2b7e98da8c15cab10263342d3f9d1",
          "id": 27,
          "name": "Daniel.Hristov"
        },
        "folderName": "Panels Library",
        "folderUid": "folder-PjWklf8Vz",
        "updated": "2023-07-07T09:44:53.96644957Z",
        "updatedBy": {
          "avatarUrl": "/avatar/4ef2b7e98da8c15cab10263342d3f9d1",
          "id": 27,
          "name": "Daniel.Hristov"
        }
      },
      "name": "TikTok Top Videos Title",
      "uid": "22IZBlrVk",
      "version": 1
    },
    "options": {
      "code": {
        "language": "plaintext",
        "showLineNumbers": false,
        "showMiniMap": false
      },
      "content": "<span style=\"font-family:Arial; font-size:2.3em;\">Top Videos | ${Zeitraum:text}</span>",
      "mode": "markdown"
    },
    "pluginVersion": "9.2.3",
    "targets": [
      {
        "dataset": "Quintly",
        "datasource": {
          "type": "grafana-bigquery-datasource",
          "uid": "qUaUqEk4k"
        },
        "editorMode": "code",
        "format": 1,
        "location": "europe-west3",
        "project": "ndr-code-bi-dashboard",
        "rawQuery": true,
        "rawSql": "SELECT  CONCAT(REPEAT(\" \", 24 - CHAR_LENGTH('Top posts')), 'Top posts')\nFROM(\nSELECT 'Top posts' as Interaktionen\nFROM `ndr-code-bi-dashboard.Quintly.facebook`\nLIMIT 1\n)",
        "refId": "A",
        "sql": {
          "columns": [
            {
              "parameters": [
                {
                  "name": "page_engaged_users",
                  "type": "functionParameter"
                }
              ],
              "type": "function"
            }
          ],
          "groupBy": [
            {
              "property": {
                "type": "string"
              },
              "type": "groupBy"
            }
          ],
          "limit": 50,
          "whereJsonTree": {
            "children1": {
              "baa899a9-cdef-4012-b456-718364767b70": {
                "properties": {
                  "field": "profileId",
                  "operator": "equal",
                  "value": [
                    null
                  ],
                  "valueSrc": [
                    "value"
                  ],
                  "valueType": [
                    "number"
                  ]
                },
                "type": "rule"
              }
            },
            "id": "b8aaaa8b-0123-4456-b89a-b18364767b70",
            "type": "group"
          }
        },
        "table": "facebookInsights"
      }
    ],
    "transformations": [
      {
        "id": "organize",
        "options": {
          "excludeByName": {
            "f0_": false
          },
          "indexByName": {},
          "renameByName": {
            "f0_": " "
          }
        }
      }
    ],
    "transparent": true,
    "type": "text"
  },
  "version": 1,
  "meta": {
    "folderName": "Panels Library",
    "folderUid": "folder-PjWklf8Vz",
    "connectedDashboards": 2,
    "created": "2024-06-20T11:45:29Z",
    "updated": "2024-06-20T11:45:29Z",
    "createdBy": {
      "avatarUrl": "/avatar/aecb468cb76f7c30d1d59a32a15dbb5e",
      "id": 2,
      "name": "sa-1-test-importer"
    },
    "updatedBy": {
      "avatarUrl": "/avatar/aecb468cb76f7c30d1d59a32a15dbb5e",
      "id": 2,
      "name": "sa-1-test-importer"
    }
  }
}
